LICENSE.txt
MANIFEST.in
README.rst
setup.py
PyGlobalShortcut.egg-info/PKG-INFO
PyGlobalShortcut.egg-info/SOURCES.txt
PyGlobalShortcut.egg-info/dependency_links.txt
PyGlobalShortcut.egg-info/top_level.txt
examples/simple.py
lib/qxtglobalshortcut.pro
libqxt/src/core/qxtglobal.cpp
libqxt/src/core/qxtglobal.h
libqxt/src/widgets/qxtglobalshortcut.cpp
libqxt/src/widgets/qxtglobalshortcut.h
libqxt/src/widgets/qxtglobalshortcut_p.h
libqxt/src/widgets/mac/qxtglobalshortcut_mac.cpp
libqxt/src/widgets/win/qxtglobalshortcut_win.cpp
libqxt/src/widgets/x11/qxtglobalshortcut_x11.cpp
pygs/configure.py
pygs/sip/pygsmod.sip
pygs/sip/qxtglobalshortcut.sip