Metadata-Version: 1.1
Name: PyGlobalShortcut
Version: 0.2.1
Summary: Python bindings to libqxt's QxtGlobalShortcut
Home-page: https://github.com/Asvel/pygs
Author: Asvel
Author-email: fe.asvel@gmail.com
License: GPLv3
Keywords: shortcut hotkey QxtGlobalShortcut libqxt qt
Platform: UNKNOWN
Classifier: Development Status :: 4 - Beta
Classifier: Environment :: MacOS X
Classifier: Environment :: Win32 (MS Windows)
Classifier: Environment :: X11 Applications :: Qt
Classifier: Intended Audience :: Developers
Classifier: Topic :: Desktop Environment
Classifier: Topic :: Software Development :: Libraries :: Python Modules
Classifier: Topic :: Software Development :: User Interfaces
Classifier: License :: OSI Approved :: GNU General Public License v3 (GPLv3)
Classifier: Programming Language :: Python :: 2
Classifier: Programming Language :: Python :: 2.7
Classifier: Programming Language :: Python :: 3
Classifier: Programming Language :: Python :: 3.1
Classifier: Programming Language :: Python :: 3.2
Classifier: Programming Language :: Python :: 3.3
